pylenium/conditions.py
pylenium/locator.py
pylenium/pylenium.py
pylenium/__init__.py
pylenium-1.0.dist-info/top_level.txt
pylenium-1.0.dist-info/METADATA
pylenium-1.0.dist-info/DESCRIPTION.rst
pylenium-1.0.dist-info/metadata.json
pylenium-1.0.dist-info/WHEEL
pylenium-1.0.dist-info/RECORD
