Metadata-Version: 1.1
Name: pylenium
Version: 1.0
Summary: A wrapper around Selenium with a more pythonic interface
Home-page: https://bitbucket.org/JanKanis/pylenium
Author: Jan Kanis
Author-email: jan.code@jankanis.nl
License: Apache Software License
Keywords: selenium
Platform: UNKNOWN
Classifier: Development Status :: 4 - Beta
Classifier: Intended Audience :: Developers
Classifier: Topic :: Software Development :: Libraries
Classifier: Topic :: Software Development :: Testing
Classifier: License :: OSI Approved :: Apache Software License
Classifier: Programming Language :: Python :: 2
Classifier: Programming Language :: Python :: 2.7
Classifier: Programming Language :: Python :: 3
Classifier: Programming Language :: Python :: 3.4
